Metadata-Version: 2.1
Name: http-pyparser
Version: 0.3.0
Summary: Parse HTTP messages simply and quickly with Python
Home-page: https://github.com/jaedsonpys/http-pyparser
Author: Jaedson Silva
Author-email: imunknowuser@protonmail.com
License: Apache 2.0
Keywords: http,parser,python,request
Platform: any
Classifier: Development Status :: 5 - Production/Stable
Classifier: Environment :: Other Environment
Classifier: Intended Audience :: Developers
Classifier: License :: OSI Approved :: Apache Software License
Classifier: Programming Language :: Python
Classifier: Programming Language :: Python :: 3
Classifier: Topic :: Internet
Classifier: Topic :: Utilities
Classifier: Topic :: Software Development :: Libraries :: Python Modules
Requires-Python: >= 3.6
License-File: LICENSE
